aiogram3_calendar/__init__.py
aiogram3_calendar/calendar_types.py
aiogram3_calendar/dialog_calendar.py
aiogram3_calendar/simple_calendar.py
aiogram3_calendar/tests/__init__.py
aiogram3_calendar/tests/test_dialog_calendar.py
aiogram3_calendar/tests/test_simple_calendar.py
aiogram3_calendar-0.1.2.dist-info/LICENSE.txt
aiogram3_calendar-0.1.2.dist-info/METADATA
aiogram3_calendar-0.1.2.dist-info/WHEEL
aiogram3_calendar-0.1.2.dist-info/top_level.txt
aiogram3_calendar-0.1.2.dist-info/RECORD
