Metadata-Version: 2.1
Name: aiogram3-calendar
Version: 0.1.2
Summary: Simple Inline Calendar & Date Selection tool for Aiogram (version 3.0.0b6 and upper) Telegram bots
Author: Andrew Nikolabay
Author-email: o-murphy <thehelixpg@gmail.com>
Project-URL: Homepage, https://github.com/o-murphy/aiogram3_calendar
Project-URL: Bug Reports, https://github.com/o-murphy/aiogram3_calendar/issues
Project-URL: Source, https://github.com/o-murphy/aiogram3_calendar
Keywords: Aiogram,Aiogram3,Telegram,Bots,Calendar
Classifier: Intended Audience :: Developers
Classifier: Natural Language :: English
Classifier: Programming Language :: Python
Classifier: Topic :: Software Development :: Libraries :: Python Modules
Classifier: Programming Language :: Python :: 3
Classifier: Programming Language :: Python :: 3 :: Only
Classifier: Programming Language :: Python :: 3.9
Classifier: Programming Language :: Python :: 3.10
Classifier: Programming Language :: Python :: 3.11
Classifier: Programming Language :: Python :: 3.12
Classifier: Operating System :: OS Independent
Classifier: Programming Language :: Python :: Implementation :: CPython
Requires-Python: >=3.9
License-File: LICENSE.txt
Requires-Dist: aiohttp==3.9.0b0; python_version == "3.12"
Requires-Dist: aiogram>=3.0.0b6
Provides-Extra: dev
Requires-Dist: flake8; extra == "dev"
Requires-Dist: pytest; extra == "dev"
Requires-Dist: pytest-cov; extra == "dev"
Requires-Dist: pytest-asyncio; extra == "dev"
Requires-Dist: pylint; extra == "dev"
